README.md
luckysocial.py
setup.cfg
setup.py
luckysocial.egg-info/PKG-INFO
luckysocial.egg-info/SOURCES.txt
luckysocial.egg-info/dependency_links.txt
luckysocial.egg-info/entry_points.txt
luckysocial.egg-info/requires.txt
luckysocial.egg-info/top_level.txt