Metadata-Version: 2.1
Name: luckysocial
Version: 0.0.6
Summary: lookup social media accounts for names
Home-page: https://github.com/edsu/luckysocial
Author: Ed Summers
Author-email: ehs@pobox.com
License: UNKNOWN
Platform: UNKNOWN
